{"openapi":"3.0.0","info":{"title":"Practica angular","version":"1.0.0"},"servers":[{"url":"http://localhost:3002/"}],"paths":{"/banner":{"get":{"description":"","responses":{"200":{"description":"","content":{"application/json":{}},"headers":{"Access-Control-Allow-Origin":{"schema":{"type":"string"},"example":"*"},"Access-Control-Allow-Methods":{"schema":{"type":"string"},"example":"GET,POST,PUT,PATCH,DELETE,HEAD,OPTIONS"},"Access-Control-Allow-Headers":{"schema":{"type":"string"},"example":"Content-Type, Origin, Accept, Authorization, Content-Length, X-Requested-With"}}}}}},"/cards":{"get":{"description":"","responses":{"200":{"description":"","content":{"application/json":{}},"headers":{"Access-Control-Allow-Origin":{"schema":{"type":"string"},"example":"*"},"Access-Control-Allow-Methods":{"schema":{"type":"string"},"example":"GET,POST,PUT,PATCH,DELETE,HEAD,OPTIONS"},"Access-Control-Allow-Headers":{"schema":{"type":"string"},"example":"Content-Type, Origin, Accept, Authorization, Content-Length, X-Requested-With"}}}}}},"/womenClothes":{"get":{"description":"","responses":{"200":{"description":"","content":{"application/json":{}},"headers":{"Access-Control-Allow-Origin":{"schema":{"type":"string"},"example":"*"},"Access-Control-Allow-Methods":{"schema":{"type":"string"},"example":"GET,POST,PUT,PATCH,DELETE,HEAD,OPTIONS"},"Access-Control-Allow-Headers":{"schema":{"type":"string"},"example":"Content-Type, Origin, Accept, Authorization, Content-Length, X-Requested-With"}}}}}},"/menClothes":{"get":{"description":"","responses":{"200":{"description":"","content":{"application/json":{}},"headers":{"Access-Control-Allow-Origin":{"schema":{"type":"string"},"example":"*"},"Access-Control-Allow-Methods":{"schema":{"type":"string"},"example":"GET,POST,PUT,PATCH,DELETE,HEAD,OPTIONS"},"Access-Control-Allow-Headers":{"schema":{"type":"string"},"example":"Content-Type, Origin, Accept, Authorization, Content-Length, X-Requested-With"}}}}}},"/kidClothes":{"get":{"description":"","responses":{"200":{"description":"","content":{"application/json":{}},"headers":{"Access-Control-Allow-Origin":{"schema":{"type":"string"},"example":"*"},"Access-Control-Allow-Methods":{"schema":{"type":"string"},"example":"GET,POST,PUT,PATCH,DELETE,HEAD,OPTIONS"},"Access-Control-Allow-Headers":{"schema":{"type":"string"},"example":"Content-Type, Origin, Accept, Authorization, Content-Length, X-Requested-With"}}}}}},"/articles":{"get":{"description":"","responses":{"200":{"description":"","content":{"application/json":{}},"headers":{"Access-Control-Allow-Origin":{"schema":{"type":"string"},"example":"*"},"Access-Control-Allow-Methods":{"schema":{"type":"string"},"example":"GET,POST,PUT,PATCH,DELETE,HEAD,OPTIONS"},"Access-Control-Allow-Headers":{"schema":{"type":"string"},"example":"Content-Type, Origin, Accept, Authorization, Content-Length, X-Requested-With"}}}}}}}}